qualytics/__init__.py
qualytics/config.py
qualytics/qualytics.py
qualytics/api/__init__.py
qualytics/api/anomalies.py
qualytics/api/client.py
qualytics/api/comments.py
qualytics/api/common.py
qualytics/api/connections.py
qualytics/api/container_profiles.py
qualytics/api/container_scans.py
qualytics/api/containers.py
qualytics/api/datastores.py
qualytics/api/field_profiles.py
qualytics/api/fields.py
qualytics/api/flows.py
qualytics/api/integrations.py
qualytics/api/license.py
qualytics/api/notifications.py
qualytics/api/operations.py
qualytics/api/partitions.py
qualytics/api/quality_checks.py
qualytics/api/scim.py
qualytics/api/tags.py
qualytics/api/teams.py
qualytics/api/user_tokens.py
qualytics/api/users.py
qualytics/cli/__init__.py
qualytics/cli/checks.py
qualytics/cli/computed_tables.py
qualytics/cli/datastores.py
qualytics/cli/main.py
qualytics/cli/operations.py
qualytics/cli/schedule.py
qualytics/services/__init__.py
qualytics/services/containers.py
qualytics/services/datastores.py
qualytics/services/operations.py
qualytics/services/quality_checks.py
qualytics/utils/__init__.py
qualytics/utils/file_ops.py
qualytics/utils/validation.py
qualytics/utils/yaml_loader.py
qualytics_cli-0.4.0.dist-info/licenses/LICENSE
qualytics_cli-0.4.0.dist-info/METADATA
qualytics_cli-0.4.0.dist-info/WHEEL
qualytics_cli-0.4.0.dist-info/entry_points.txt
qualytics_cli-0.4.0.dist-info/top_level.txt
qualytics_cli-0.4.0.dist-info/RECORD
