Metadata-Version: 2.4
Name: qualytics-cli
Version: 0.4.0
Summary: Qualytics CLI
Author-email: Qualytics <devops@qualytics.co>
License-Expression: MIT
Project-URL: Homepage, https://www.qualytics.co/
Project-URL: GitHub, https://github.com/Qualytics/qualytics-cli
Project-URL: Userguide, https://qualytics.github.io/userguide/
Keywords: Qualytics,Data Quality
Classifier: Programming Language :: Python :: 3
Classifier: Programming Language :: Python :: 3.9
Classifier: Programming Language :: Python :: 3.10
Classifier: Programming Language :: Python :: 3.11
Classifier: Programming Language :: Python :: 3.12
Classifier: Programming Language :: Python :: 3.13
Classifier: Operating System :: OS Independent
Requires-Python: >=3.9
License-File: LICENSE
Requires-Dist: typer
Requires-Dist: requests
Requires-Dist: pyjwt
Requires-Dist: croniter
Requires-Dist: typing-extensions
Requires-Dist: rich
Requires-Dist: shellingham
Requires-Dist: click
Requires-Dist: python-dotenv
Requires-Dist: pyyaml
Requires-Dist: urllib3
Requires-Dist: openpyxl
Provides-Extra: dev
Requires-Dist: ruff>=0.1.0; extra == "dev"
Requires-Dist: pre-commit>=3.0.0; extra == "dev"
Requires-Dist: bump2version; extra == "dev"
Dynamic: license-file
